ml_ms4alg_snippets/__init__.py
ml_ms4alg_snippets/ms4alg_snippets.py
ml_ms4alg_snippets/ms4alg_snippets_spec.py.mp
ml_ms4alg_snippets/p_ms4alg_snippets.py
ml_ms4alg_snippets-0.1.11.dist-info/METADATA
ml_ms4alg_snippets-0.1.11.dist-info/RECORD
ml_ms4alg_snippets-0.1.11.dist-info/WHEEL
ml_ms4alg_snippets-0.1.11.dist-info/top_level.txt
