Metadata-Version: 2.1
Name: ml-ms4alg-snippets
Version: 0.1.11
Summary: Mountainsort v4 for MountainLab - Snippets Version
Home-page: https://github.com/GeoffBarrett/ml_ms4alg_snippets
Author: Geoffrey Barrett
Author-email: gmbarrett313@gmail.com
License: UNKNOWN
Platform: UNKNOWN
Classifier: Programming Language :: Python :: 3
Classifier: License :: OSI Approved :: Apache Software License
Classifier: Operating System :: OS Independent
Requires-Dist: pybind11
Requires-Dist: isosplit5
Requires-Dist: numpy
Requires-Dist: mountainlab-pytools
Requires-Dist: h5py
